ogdrb/__init__.py
ogdrb/converters.py
ogdrb/main.py
ogdrb/organizer.py
ogdrb/py.typed
ogdrb/services.py
ogdrb/utils.py
ogdrb-0.4.3.dist-info/METADATA
ogdrb-0.4.3.dist-info/WHEEL
ogdrb-0.4.3.dist-info/licenses/LICENSE
ogdrb-0.4.3.dist-info/RECORD
