Metadata-Version: 2.4
Name: ogdrb
Version: 0.4.3
Summary: OpenGD77 + RepeaterBook
Project-URL: homepage, https://github.com/MicaelJarniac/ogdrb
Project-URL: source, https://github.com/MicaelJarniac/ogdrb
Project-URL: download, https://pypi.org/project/ogdrb/#files
Project-URL: changelog, https://github.com/MicaelJarniac/ogdrb/blob/main/docs/CHANGELOG.md
Project-URL: documentation, https://ogdrb.readthedocs.io
Project-URL: issues, https://github.com/MicaelJarniac/ogdrb/issues
Author-email: Micael Jarniac <micael@jarniac.dev>
License: MIT
License-File: LICENSE
Classifier: Development Status :: 1 - Planning
Classifier: License :: OSI Approved :: MIT License
Classifier: Natural Language :: English
Classifier: Operating System :: OS Independent
Classifier: Programming Language :: Python :: 3
Classifier: Typing :: Typed
Requires-Python: >=3.13
Requires-Dist: anyio>=4.9.0
Requires-Dist: attrs>=25.3.0
Requires-Dist: haversine>=2.9.0
Requires-Dist: loguru>=0.7.3
Requires-Dist: nicegui>=2.17.0
Requires-Dist: opengd77>=0.3.0
Requires-Dist: pycountry>=24.6.1
Requires-Dist: pydantic-settings>=2.9.1
Requires-Dist: pydantic>=2.11.2
Requires-Dist: repeaterbook>=0.2.1
Requires-Dist: sqlmodel>=0.0.24
